hostsmate_src/__init__.py
hostsmate_src/autorunner.py
hostsmate_src/domains_extractor.py
hostsmate_src/execute.py
hostsmate_src/logger.py
hostsmate_src/suspender.py
hostsmate_src/system_hosts_file.py
hostsmate_src/unique_blacklisted_domains.py
hostsmate_src/cli/__init__.py
hostsmate_src/cli/cli_method_executor.py
hostsmate_src/cli/parser.py
hostsmate_src/cli/prompt.py
hostsmate_src/sources/__init__.py
hostsmate_src/sources/blacklist_sources.py
hostsmate_src/sources/sources.py
hostsmate_src/sources/whitelist_sources.py
resources/__init__.py
resources/anacron_job_setter.sh
resources/blacklist_sources.json
resources/hosts_header
resources/whitelist_sources.json
tests/__init__.py
tests/hostsmate_tests/__init__.py
tests/hostsmate_tests/autorunner_test.py
tests/hostsmate_tests/domains_extractor_test.py
tests/hostsmate_tests/logger_test.py
tests/hostsmate_tests/suspender_test.py
tests/hostsmate_tests/system_hosts_file_test.py
tests/hostsmate_tests/unique_blacklisted_domains_test.py
tests/hostsmate_tests/cli/__init__.py
tests/hostsmate_tests/cli/cli_method_executor_test.py
tests/hostsmate_tests/cli/parser_test.py
tests/hostsmate_tests/cli/prompt_test.py
tests/hostsmate_tests/sources/__init__.py
tests/hostsmate_tests/sources/blacklist_sources_test.py
tests/hostsmate_tests/sources/sources_test.py
tests/hostsmate_tests/sources/whitelist_sources_test.py
tests/os_utils_tests/__init__.py
tests/os_utils_tests/os_utils_test.py
tests/os_utils_tests/str_utils_test.py
tests/utils_tests/__init__.py
tests/utils_tests/os_utils_test.py
tests/utils_tests/str_utils_test.py
utils/__init__.py
utils/os_utils.py
utils/str_utils.py
hostsmate-1.0.2.dist-info/LICENSE
hostsmate-1.0.2.dist-info/METADATA
hostsmate-1.0.2.dist-info/WHEEL
hostsmate-1.0.2.dist-info/entry_points.txt
hostsmate-1.0.2.dist-info/top_level.txt
hostsmate-1.0.2.dist-info/RECORD
