Metadata-Version: 2.1
Name: hostsmate
Version: 1.0.2
Summary: Anti-malware, ad-blocking, and tracking protection tool that populates and manages the Hosts file.
Home-page: https://github.com/kravchenkoda/hostsmate
Author: Dmytro Kravchenko
Author-email: dmytro.kravchenko@gmx.com
License: MIT
Classifier: Operating System :: POSIX
Classifier: License :: OSI Approved :: MIT License
Classifier: Topic :: Security
Classifier: Topic :: Internet :: Name Service (DNS)
Classifier: Topic :: Utilities
Classifier: Intended Audience :: End Users/Desktop
Classifier: Intended Audience :: System Administrators
Classifier: Intended Audience :: Developers
Classifier: Environment :: Console
Requires-Python: >=3.10.6
License-File: LICENSE
Requires-Dist: requests (==2.25.1)
Provides-Extra: dev
Requires-Dist: pytest (==7.2.2) ; extra == 'dev'
Requires-Dist: pytest-cov (==4.0.0) ; extra == 'dev'
Requires-Dist: responses (==0.23.1) ; extra == 'dev'
Requires-Dist: freezegun (==1.2.2) ; extra == 'dev'
Requires-Dist: flake8 (==6.0.0) ; extra == 'dev'
